upd_skill/__init__.py
upd_skill-0.1.1.dist-info/METADATA
upd_skill-0.1.1.dist-info/WHEEL
upd_skill-0.1.1.dist-info/entry_points.txt
upd_skill-0.1.1.dist-info/RECORD
