Metadata-Version: 2.4
Name: upd-skill
Version: 0.1.1
Summary: CLI tool for updating Claude Code, Codex, OpenCode, Amp, Clawdbot agent skills.
License-Expression: MIT
Requires-Python: >=3.10
Requires-Dist: agent-skills-upd>=0.1.1
